{
	"column-insert": {
		"label": "Column before",
		"description": "Insert a new table column before selected column",
		"elements": [
			"entry"
		],
		"steps": {
			"type": "command/column-insert"

		}
	},"column-after-insert": {
		"label": "Column after",
		"description": "Insert a new table column after selected column",
		"elements": [
			"entry"
		],
		"steps": {
			"type": "command/column-insert",
			"data": {
				"insertAfter": true
			}
		}
	},
	"column-delete": {
		"label": "Delete column",
		"description": "Delete the selected table column.",
		"elements": [
			"entry"
		],
		"steps": {
			"type": "command/column-delete"
		}
	},
	"convert-to-row": {
		"label": "Convert header row to row",
		"description": "Convert the current selected header row into a row.",
		"elements": [
			"entry"
		],
		"steps": {
			"type": "command/convert-to-row"
		}
	},
	"convert-to-header": {
		"label": "Convert row to header row",
		"description": "Convert the current selected row into a header row.",
		"elements": [
			"entry"
		],
		"steps": {
			"type": "command/convert-to-header",
			"data": {
				"rowCount": 0
			}
		}
	},
	"convert-firstrow-to-header": {
		"label": "Convert first row to header row",
		"description": "Convert the first row into a header row.",
		"elements": [
			"entry"
		],
		"steps": {
			"type": "command/convert-to-header",
			"data": {
				"rowCount": 1
			}
		}
	},
	"convert-firsttworows-to-header": {
		"label": "Convert first two rows to header rows",
		"description": "Convert the first two rows into a header rows.",
		"elements": [
			"entry"
		],
		"steps": {
			"type": "command/convert-to-header",
			"data": {
				"rowCount": 2
			}
		}
	},
	"convert-firstthreerows-to-header": {
		"label": "Convert first three rows to header rows",
		"description": "Convert the first three rows into a header rows.",
		"elements": [
			"entry"
		],
		"steps": {
			"type": "command/convert-to-header",
			"data": {
				"rowCount": 3
			}
		}
	},
	"row-insert": {
		"label": "Row before",
		"description": "Insert a new table row before selected row",
		"elements": [
			"row"
		],
		"steps": {
			"type": "command/row-insert"
		}
	},
	"row-after-insert": {
		"label": "Row after",
		"description": "Insert a new table row after selected row",
		"elements": [
			"row"
		],
		"steps": {
			"type": "command/row-insert",
			"data": {
				"insertAfter": true
			}
		}
	},
	"row-delete": {
		"label": "Delete row",
		"description": "Delete the selected table row.",
		"elements": [
			"row"
		],
		"steps": {
			"type": "command/row-delete"
		}
	},
	"split-cell-completely": {
		"label": "Split cell completely",
		"description": "Split the cell to 1 by 1 cells",
		"elements": [
			"entry"
		],
		"steps": {
			"type": "command/split-cell",
			"data": {
				"splitMode": "completely"
			}
		}
	},
	"split-cell-into-rows": {
		"label": "Split cell into rows",
		"description": "Split the cell's rowspan in half",
		"elements": [
			"entry"
		],
		"steps": {
			"type": "command/split-cell",
			"data": {
				"splitMode": "intoRows"
			}
		}
	},
	"split-cell-into-columns": {
		"label": "Split cell into columns",
		"description": "Split the cell's columnsspan in half",
		"elements": [
			"entry"
		],
		"steps": {
			"type": "command/split-cell",
			"data": {
				"splitMode": "intoColumns"
			}
		}
	},
	"merge-cell-right": {
		"label": "Merge cell with cell to the right",
		"description": "Merge cell with the cell(s) to the right",
		"elements": [
			"entry"
		],
		"steps": {
			"type": "command/merge-cell",
			"data": {
				"mergeMode": "mergeRight"
			}
		}
	}
	,
	"merge-cell-left": {
		"label": "Merge cell with cell to the left",
		"description": "Merge cell with the cell(s) to the left",
		"elements": [
			"entry"
		],
		"steps": {
			"type": "command/merge-cell",
			"data": {
				"mergeMode": "mergeLeft"
			}
		}
	}
	,
	"merge-cell-above": {
		"label": "Merge cell with cell above",
		"description": "Merge cell with the cell(s) above",
		"elements": [
			"entry"
		],
		"steps": {
			"type": "command/merge-cell",
			"data": {
				"mergeMode": "mergeAbove"
			}
		}
	},
	"merge-cell-below": {
		"label": "Merge cell with cell below",
		"description": "Merge cell with the cell(s) below",
		"elements": [
			"entry"
		],
		"steps": {
			"type": "command/merge-cell",
			"data": {
				"mergeMode": "mergeBelow"
			}
		}
	},
	"set-table-styling": {
		"label": "With borders, with heading",
		"description": "With borders, with heading style for selected table.",
		"elements": [
			"table"
		],
		"steps": {
			"type": "command/set-table-styling",
			"data": {
				"hasHeader": true,
				"hasBorders": true
			}
		}
	},
	"set-table-styling-borderless-headerless": {
		"label": "Without borders, without heading",
		"description": "Without borders, without heading style for selected table.",
		"elements": [
			"table"
		],
		"steps": {
			"type": "command/set-table-styling",
			"data": {
				"hasHeader": false,
				"hasBorders": false
			}
		}
	},
	"set-table-styling-borderless": {
		"label": "Without borders, with heading",
		"description": "Without borders, with heading style for selected table.",
		"elements": [
			"table"
		],
		"steps": {
			"type": "command/set-table-styling",
			"data": {
				"hasHeader": true,
				"hasBorders": false
			}
		}
	},
	"set-table-styling-headerless": {
		"label": "With borders, without heading",
		"description": "With borders, without heading style for selected table.",
		"elements": [
			"table"
		],
		"steps": {
			"type": "command/set-table-styling",
			"data": {
				"hasHeader": false,
				"hasBorders": true
			}
		}
	},
	"table-insert": {
		"label": "Table: 2 x 2",
		"description": "Insert a table",
		"icon": "table",
		"elements": [
			"table"
		],
		"steps": {
			"type": "command/table-insert",
			"data": {
				"hasHeader": true,
				"rows": 2,
				"columns": 2
			}
		}
	},
	"table-insert-three": {
		"label": "Table: 3 x 3",
		"description": "Insert a table",
		"icon": "table",
		"elements": [
			"table"
		],
		"steps": {
			"type": "command/table-insert",
			"data": {
				"hasHeader": true,
				"rows": 3,
				"columns": 3
			}
		}
	},
	"table-insert-four": {
		"label": "Table: 4 x 4",
		"description": "Insert a table",
		"icon": "table",
		"elements": [
			"table"
		],
		"steps": {
			"type": "command/table-insert",
			"data": {
				"hasHeader": true,
				"rows": 4,
				"columns": 4
			}
		}
	},
	"table-insert-five": {
		"label": "Table: 5 x 5",
		"description": "Insert a table",
		"icon": "table",
		"elements": [
			"table"
		],
		"steps": {
			"type": "command/table-insert",
			"data": {
				"hasHeader": true,
				"rows": 5,
				"columns": 5
			}
		}
	},
	"set-cell-horizontal-alignment-left": {
		"label": "Left",
		"description": "Align the cells content to the left.",
		"icon": "align-left",
		"elements": [
			"entry"
		],
		"steps": {
			"type": "command/set-cell-horizontal-alignment",
			"data": {
				"horizontalAlignment": "left"
			}
		}
	},
	"set-cell-horizontal-alignment-right": {
		"label": "Right",
		"description": "Align the cells content to the right.",
		"icon": "align-right",
		"elements": [
			"entry"
		],
		"steps": {
			"type": "command/set-cell-horizontal-alignment",
			"data": {
				"horizontalAlignment": "right"
			}
		}
	},
	"set-cell-horizontal-alignment-center": {
		"label": "Center",
		"description": "Align the cells content to the center.",
		"icon": "align-center",
		"elements": [
			"entry"
		],
		"steps": {
			"type": "command/set-cell-horizontal-alignment",
			"data": {
				"horizontalAlignment": "center"
			}
		}
	},
	"set-cell-horizontal-alignment-justify": {
		"label": "Justify",
		"description": "Align the cells content to the left and right.",
		"icon": "align-justify",
		"elements": [
			"entry"
		],
		"steps": {
			"type": "command/set-cell-horizontal-alignment",
			"data": {
				"horizontalAlignment": "justify"
			}
		}
	},
	"set-cell-vertical-alignment-top": {
		"label": "Top",
		"description": "Align the cells content to the top.",
		"elements": [
			"entry"
		],
		"steps": {
			"type": "command/set-cell-vertical-alignment",
			"data": {
				"verticalAlignment": "top"
			}
		}
	},
	"set-cell-vertical-alignment-bottom": {
		"label": "Bottom",
		"description": "Align the cells content to the bottom.",
		"elements": [
			"entry"
		],
		"steps": {
			"type": "command/set-cell-vertical-alignment",
			"data": {
				"verticalAlignment": "bottom"
			}
		}
	},
	"set-cell-vertical-alignment-center": {
		"label": "Center",
		"description": "Align the cells content to the center.",
		"elements": [
			"entry"
		],
		"steps": {
			"type": "command/set-cell-vertical-alignment",
			"data": {
				"verticalAlignment": "middle"
			}
		}
	}
}
